Workbook

Sheet Mechanical
A1: ENGG.tv Contents
A3: Subject | B3: Chapters | C3: Topics | D3: Video Notes | E3: Theory Questions | F3: Numericals | G3: Vid Explanation | H3: Homework/Solution
A4: Mathematics | B4: Math Basics | C4: Trigonometry | D4: 3 | E4: 5 | F4: 6 | G4: 0 | H4: 1
C5: Logarithms | D5: 0 | E5: 4 | F5: 5 | G5: 0 | H5: 1
C6: Areas and Volumes | D6: 0 | E6: 0 | F6: 5 | G6: 0 | H6: 1
C7: Theory of Complex Numbers | D7: 0 | E7: 6 | F7: 5 | G7: 0 | H7: 0
C8: Calculators | D8: 0 | E8: 0 | F8: 2 | G8: 0 | H8: 0
B9: Analytic Geometry | C9: Straight Lines | D9: 1 | E9: 6 | F9: 8 | G9: 3 | H9: 1
C10: Conics | D10: 1 | E10: 2 | F10: 5 | G10: 0 | H10: 0
C11: Circles | D11: 2 | E11: 4 | F11: 9 | G11: 2 | H11: 1
C13: Ellipse | D13: 1 | E13: 2 | F13: 5 | G13: 1 | H13: 1
C14: Parabola | D14: 1 | E14: 3 | F14: 7 | G14: 0 | H14: 1
C15: Hyperbola | D15: 1 | E15: 2 | F15: 6 | G15: 1 | H15: 1
B16: Calculus | C16: Limits | D16: 1 | E16: 5 | F16: 5 | G16: 1 | H16: 1
C17: Derivative | D17: 1 | E17: 2 | F17: 5 | G17: 0 | H17: 1
C18: Application of Derivatives | D18: 2 | E18: 6 | F18: 5 | G18: 0 | H18: 1
C19: Partial Derivatives | D19: 0 | E19: 3 | F19: 2 | G19: 1 | H19: 1
C20: Indefinite Integrals | D20: 1 | E20: 0 | F20: 5 | G20: 0 | H20: 0
B21: Differential Equations | C21: General Terminology | D21: 1 | E21: 5 | F21: 0 | G21: 0 | H21: 0
C22: First Order DE | D22: 1 | E22: 2 | F22: 7 | G22: 0 | H22: 0
C23: Higher Order DE | D23: 4 | E23: 0 | F23: 5 | G23: 1 | H23: 1
C24: Laplace Transform | D24: 1 | E24: 3 | F24: 5 | G24: 1 | H24: 1
B25: Linear Algebra | C25: Determinant of a Matrix | D25: 0 | E25: 3 | F25: 2 | G25: 0 | H25: 0
C27: Matrix Operations | D27: 0 | E27: 2 | F27: 5 | G27: 0 | H27: 0
C28: Unit Vector | D28: 1 | E28: 6 | F28: 6 | G28: 0 | H28: 0
C29: Dot and Cross Products | D29: 2 | E29: 5 | F29: 7 | G29: 1 | H29: 0
C30: Gradient, Divergence and Curl | D30: 1 | E30: 2 | F30: 8 | G30: 0 | H30: 1
B33: Numerical Methods | C33: Newton’s Method of Root Extraction | D33: 1 | E33: 2 | F33: 5 | G33: 0 | H33: 1
C34: Newton’s Method of Minimization | D34: 0 | E34: 0 | F34: 2 | G34: 0 | H34: 0
C35: Forward Rectangle Rule | D35: 1 | E35: 2 | F35: 2 | G35: 0 | H35: 1
C36: Trapezoidal Rule | D36: 1 | E36: 2 | F36: 5 | G36: 1 | H36: 1
C37: Simpson’s Rule | D37: 0 | E37: 0 | F37: 3 | G37: 0 | H37: 0
C38: Taylor’s and McLaurin’s Series | D38: 0 | E38: 0 | F38: 2 | G38: 0 | H38: 1
B39: Algorithm and Logic Development | C39: Flowchart | D39: 1 | E39: 4 | F39: 0 | G39: 0 | H39: 1
C40: Pseudocode | D40: 0 | E40: 5 | F40: 1 | G40: 0 | H40: 0
A41: Probability and Statistics | B41: Measures of Central Tendencies and Distribution | C41: Mean, Median Mode | D41: 1 | E41: 7 | F41: 8 | G41: 0 | H41: 1
C42: Standard Deviation and Variance | D42: 0 | E42: 3 | F42: 5 | G42: 0 | H42: 0
B43: Permutations and Combinations | C43: Arrangement and Selection | D43: 1 | E43: 2 | F43: 5 | G43: 0 | H43: 0
C44: Selection with Identical Objects | D44: 0 | E44: 0 | F44: 3 | G44: 0 | H44: 0
B45: Laws of Probability | C45: Probability Concepts | D45: 1 | E45: 5 | F45: 10 | G45: 0 | H45: 1
B46: Probability Functions, Distributions and Expected Value | C46: PDF and CDF | D46: 1 | E46: 2 | F46: 3 | G46: 1 | H46: 0
C47: Binomial Distribution | D47: 1 | E47: 6 | F47: 6 | G47: 1 | H47: 1
C48: Normal Distribution | D48: 1 | E48: 10 | F48: 5 | G48: 0 | H48: 1
C49: t-distribution | D49: 1 | E49: 2 | F49: 2 | G49: 0 | H49: 0
C50: Chi-squared distribution | D50: 2 | E50: 5 | F50: 0 | G50: 0 | H50: 0
C51: Expected Value | D51: 0 | E51: 2 | F51: 3 | G51: 0 | H51: 0
B52: Propagation of Error | C52: Measurement of Error | D52: 0 | E52: 6 | F52: 0 | G52: 0 | H52: 0
C53: Linear Combinations | D53: 0 | E53: 0 | F53: 3 | G53: 0 | H53: 0
B54: Regression and Curve Fitting | C54: Linear Regression | D54: 1 | E54: 2 | F54: 5 | G54: 0 | H54: 0
C55: Correlation Coefficient | D55: 0 | E55: 2 | F55: 2 | G55: 0 | H55: 0
B56: Hypothesis Testing | C56: Null Hypothesis | D56: 0 | E56: 19 | F56: 3 | G56: 0 | H56: 0
C57: Confidence Intervals | D57: 0 | E57: 3 | F57: 2 | G57: 0 | H57: 0
C58: Comparison of Samples | D58: 0 | E58: 1 | F58: 1 | G58: 0 | H58: 0
C59: Sample Size Requirements | D59: 0 | E59: 2 | F59: 2 | G59: 0 | H59: 0
A60: Ethics and Professional Practice | B60: Codes of Ethics | C60: NCEES Model Law | D60: 0 | E60: 11 | F60: 0 | G60: 0 | H60: 0
C61: Professional and Technical Societies | D61: 0 | E61: 6 | F61: 0 | G61: 0 | H61: 0
C62: Ethical and Legal Considerations | D62: 0 | E62: 18 | F62: 0 | G62: 0 | H62: 0
B63: Public Health, Safety and Welfare | C63: Public Health, Safety and Welfare in Engineering | D63: 0 | E63: 5 | F63: 0 | G63: 0 | H63: 0
B64: Intellectual Property | C64: Introduction to Intellectual Property | D64: 0 | E64: 2 | F64: 0 | G64: 0 | H64: 0
C65: Patents and Copyrights | D65: 0 | E65: 3 | F65: 0 | G65: 0 | H65: 0
C66: Trademarks | D66: 0 | E66: 2 | F66: 0 | G66: 0 | H66: 0
C67: Trade Secrets | D67: 0 | E67: 2 | F67: 0 | G67: 0 | H67: 0
B68: Societal Considerations | C68: Life Cycle Assessment (LCA) | D68: 0 | E68: 4 | F68: 0 | G68: 0 | H68: 0
C69: Sustainability | D69: 0 | E69: 2 | F69: 0 | G69: 0 | H69: 0
A70: Engineering Economics | B70: Time Value of Money | C70: Time Value of Money | D70: 1 | E70: 2 | F70: 8 | G70: 1 | H70: 1
B71: Non-Annual Compounding | C71: Non-Annual Compounding | D71: 0 | E71: 2 | F71: 5 | G71: 0 | H71: 0
B72: Break-even Analysis | C72: Break-even Analysis | D72: 1 | E72: 11 | F72: 5 | G72: 1 | H72: 1
B73: Inflation | C73: Inflation | D73: 0 | E73: 3 | F73: 2 | G73: 0 | H73: 0
B74: Depreciation | C74: Depreciation | D74: 1 | E74: 3 | F74: 6 | G74: 0 | H74: 0
B75: Capitalized Cost | C75: Capitalized Cost | D75: 0 | E75: 3 | F75: 5 | G75: 0 | H75: 1
B76: Rate of Return | C76: Internal Rate of Return | D76: 0 | E76: 3 | F76: 3 | G76: 0 | H76: 0
B77: Benefit-Cost Analysis | C77: Benefit-Cost Analysis | D77: 0 | E77: 2 | F77: 2 | G77: 0 | H77: 0
B78: Decision Trees | C78: Decision Trees | D78: 0 | E78: 4 | F78: 2 | G78: 0 | H78: 0
B79: Expected Value and Risk | C79: Expected Value and Risk | D79: 0 | E79: 3 | F79: 2 | G79: 0 | H79: 0
A80: Electricity and Magnetism | B80: Electrical Fundamentals | C80: Coulomb’s Law | D80: 1 | E80: 5 | F80: 5 | G80: 0 | H80: 1
C81: Electrostatic Field | D81: 0 | E81: 5 | F81: 2 | G81: 1 | H81: 1
C82: Voltage | D82: 1 | E82: 6 | F82: 5 | G82: 0 | H82: 1
C83: Electric Current | D83: 0 | E83: 2 | F83: 4 | G83: 0 | H83: 1
C84: Magnetostatics | D84: 0 | E84: 6 | F84: 5 | G84: 0 | H84: 0
C85: Resistance | D85: 1 | E85: 4 | F85: 14 | G85: 0 | H85: 0
C86: Electric Power | D86: 0 | E86: 2 | F86: 5 | G86: 0 | H86: 0
C87: Kirchhoff's Laws | D87: 2 | E87: 11 | F87: 1 | G87: 0 | H87: 0
B88: Source Equivalents | C88: Thevenin Equivalent | D88: 0 | E88: 11 | F88: 1 | G88: 0 | H88: 0
C89: Norton Equivalent | D89: 0 | E89: 7 | F89: 2 | G89: 0 | H89: 0
B90: Capacitors and Inductors | C90: Energy Stored in a Capacitor or Inductor | D90: 0 | E90: 4 | F90: 4 | G90: 0 | H90: 1
C91: Capacitors and Inductors in Parallel and Series | D91: 0 | E91: 1 | F91: 3 | G91: 0 | H91: 0
B92: AC Circuits | C92: Frequency and Period of AC Waveform | D92: 0 | E92: 3 | F92: 2 | G92: 0 | H92: 0
C93: Average Value | D93: 1 | E93: 2 | F93: 1 | G93: 0 | H93: 0
C94: RMS Value | D94: 1 | E94: 2 | F94: 5 | G94: 0 | H94: 0
C95: AC Impedance | D95: 1 | E95: 8 | F95: 9 | G95: 0 | H95: 1
C96: Phasors of Pure RLC Circuits | D96: 0 | E96: 7 | F96: 5 | G96: 0 | H96: 0
C97: Admittance, Conductance and Susceptance | D97: 0 | E97: 13 | F97: 4 | G97: 0 | H97: 0
B98: Transformers | C98: Transformers | D98: 0 | E98: 7 | F98: 4 | G98: 0 | H98: 0
B99: Motors and Generators | C99: Efficiency, Losses and Power in Rotating Machines | D99: 0 | E99: 2 | F99: 1 | G99: 0 | H99: 0
C100: AC Machines (Synchronus and Induction) | D100: 0 | E100: 2 | F100: 3 | G100: 0 | H100: 0
C101: DC Machines | D101: 0 | E101: 6 | F101: 2 | G101: 0 | H101: 0
C102: Servomotors and Generators | D102: 0 | E102: 6 | F102: 2 | G102: 0 | H102: 0
A103: Statics | B103: Resultant of Force Systems | C103: Resultant of Force Systems | D103: 1 | E103: 2 | F103: 12 | G103: 0 | H103: 1
B104: Resolution of Forces | C104: Resolution of Forces | D104: 0 | E104: 6 | F104: 4 | G104: 0 | H104: 0
B105: Moment and Couple | C105: Moment and Couple | D105: 2 | E105: 4 | F105: 2 | G105: 0 | H105: 0
...

Sheet Other
A1: ENGG.tv Contents
A3: Subject | B3: Chapters | C3: Topics | D3: Video Notes | E3: Theory Questions | F3: Numericals | G3: Vid Explanation | H3: Homework/Solution
A4: Mathematics | B4: Math Basics | C4: Trigonometry | D4: ='Mechanical'!D4 -> 3 | E4: ='Mechanical'!E4 -> 5 | F4: ='Mechanical'!F4 -> 6 | G4: ='Mechanical'!G4 -> 0 | H4: ='Mechanical'!H4 -> 1
C5: Logarithms | D5: 0 | E5: 2 | F5: 3 | G5: 0 | H5: 1
C6: Areas and Volumes | D6: ='Mechanical'!D6 -> 0 | E6: ='Mechanical'!E6 -> 0 | F6: ='Mechanical'!F6 -> 5 | G6: ='Mechanical'!G6 -> 0 | H6: ='Mechanical'!H6 -> 1
C7: Theory of Complex Numbers | D7: ='Mechanical'!D7 -> 0 | E7: ='Mechanical'!E7 -> 6 | F7: ='Mechanical'!F7 -> 5 | G7: ='Mechanical'!G7 -> 0 | H7: ='Mechanical'!H7 -> 0
C8: Calculators | D8: ='Mechanical'!D8 -> 0 | E8: ='Mechanical'!E8 -> 0 | F8: ='Mechanical'!F8 -> 2 | G8: ='Mechanical'!G8 -> 0 | H8: ='Mechanical'!H8 -> 0
B9: Analytic Geometry | C9: Straight Line | D9: 1 | E9: ='Mechanical'!E9 -> 6 | F9: 8 | G9: 3 | H9: 1
C10: Conics | D10: 1 | E10: ='Mechanical'!E10 -> 2 | F10: 3 | G10: 0 | H10: 0
C11: Circle | D11: ='Mechanical'!D11 -> 2 | E11: 1 | F11: 9 | G11: 2 | H11: 1
C12: Ellipse | D12: ='Mechanical'!D13 -> 1 | E12: ='Mechanical'!E13 -> 2 | F12: ='Mechanical'!F13 -> 5 | G12: ='Mechanical'!G13 -> 1 | H12: ='Mechanical'!H13 -> 1
C13: Parabola | D13: 1 | E13: 2 | F13: 8 | G13: 0 | H13: 1
C14: Hyperbola | D14: 1 | E14: 2 | F14: 6 | G14: 1 | H14: 1
B15: Linear Algebra | C15: Determinant of a Matrix | D15: 0 | E15: 1 | F15: 2 | G15: 0 | H15: 0
C16: Matrix Operations | D16: 0 | E16: 2 | F16: 7 | G16: 0 | H16: 0
B17: Differential Equations | C17: General Terminology | D17: 1 | E17: 4 | F17: 0 | G17: 0 | H17: 0
C18: First Order DE | D18: 1 | E18: 2 | F18: 7 | G18: 0 | H18: 0
C19: Higher Order DE | D19: 4 | E19: 0 | F19: 3 | G19: 1 | H19: 0
B20: Numerical Methods | C20: Newton’s Method of Root Extraction | D20: 1 | E20: 2 | F20: 3 | G20: 0 | H20: 1
C21: Newton’s Method of Minimization | D21: 0 | E21: 0 | F21: 2 | G21: 0 | H21: 0
C22: Forward Rectangle Rule | D22: 1 | E22: 2 | F22: 2 | G22: 0 | H22: 1
C23: Trapezoidal Rule | D23: 1 | E23: 2 | F23: 4 | G23: 1 | H23: 1
C24: Simpson’s Rule | D24: 0 | E24: 0 | F24: 2 | G24: 0 | H24: 0
C25: Taylor’s and McLaurin’s Series | D25: 0 | E25: 0 | F25: 2 | G25: 0 | H25: 1
B26: Single Variable Calculus | C26: Limits | D26: 0 | E26: 2 | F26: 2 | G26: 0 | H26: 1
C27: Derivative | D27: 1 | E27: 2 | F27: 3 | G27: 0 | H27: 1
C28: Application of Derivatives | D28: 0 | E28: 3 | F28: 0 | G28: 0 | H28: 1
C29: Indefinite Integrals | D29: 1 | E29: 0 | F29: 6 | G29: 0 | H29: 0
A30: Probability and Statistics | B30: Measures of Central Tendencies and Distribution | C30: Mean, Median Mode | D30: 1 | E30: 3 | F30: 9 | G30: 0 | H30: 1
C31: Standard Deviation | D31: 0 | E31: 3 | F31: 3 | G31: 0 | H31: 0
B32: Permutations and Combinations | C32: Arrangements and Selections | D32: 1 | E32: 2 | F32: 5 | G32: 0 | H32: 0
C33: Selection with Identical Objects | D33: 0 | E33: 0 | F33: 3 | G33: 0 | H33: 0
B34: Laws of Probability | C34: Probability Concepts | D34: 1 | E34: 2 | F34: 10 | G34: 0 | H34: 1
B35: Probability Functions, Distributions and Expected Values | C35: PDF and CDF | D35: 1 | E35: 2 | F35: 3 | G35: 1 | H35: 0
C36: Binomial Distribution | D36: 1 | E36: 1 | F36: 6 | G36: 1 | H36: 1
C37: Normal Distribution | D37: 1 | E37: 2 | F37: 4 | G37: 0 | H37: 1
C38: t-distribution | D38: 1 | E38: 2 | F38: 3 | G38: 0 | H38: 0
C39: Expected Value | D39: 0 | E39: 2 | F39: 4 | G39: 0 | H39: 0
B40: Propagation of Error | C40: Measurement of Error | D40: 0 | E40: 6 | F40: 0 | G40: 0 | H40: 0
C41: Linear Combinations | D41: 0 | E41: 0 | F41: 2 | G41: 0 | H41: 0
C42: Measurement Uncertainty | D42: 0 | E42: 0 | F42: 3 | G42: 0 | H42: 0
B43: Regression and Curve Fitting | C43: Linear Regression | D43: 1 | E43: 2 | F43: 4 | G43: 0 | H43: 0
C44: Correlation Coefficient | D44: 0 | E44: 2 | F44: 1 | G44: 0 | H44: 0
B45: Hypothesis Testing | C45: Null Hypothesis | D45: 0 | E45: 7 | F45: 2 | G45: 0 | H45: 0
C46: Confidence Intervals | D46: 0 | E46: 3 | F46: 2 | G46: 0 | H46: 0
C47: Comparison of Samples | D47: 0 | E47: 1 | F47: 1 | G47: 0 | H47: 0
C48: Sample Size Requirements | D48: 0 | E48: 2 | F48: 2 | G48: 0 | H48: 0
A49: Chemistry | B49: Oxidation and Reduction | C49: Oxidation and Reduction Reactions | D49: 0 | E49: 5 | F49: 0 | G49: 0 | H49: 0
C50: Corrosion Terminology | D50: 0 | E50: 2 | F50: 0 | G50: 0 | H50: 0
C51: Corrosion Mechanism | D51: 0 | E51: 3 | F51: 0 | G51: 0 | H51: 0
C52: EMF and Galvanic Series | D52: 0 | E52: 3 | F52: 0 | G52: 0 | H52: 0
C53: Corrosion Control | D53: 0 | E53: 4 | F53: 0 | G53: 0 | H53: 0
B54: Acids and Bases | C54: pH | D54: 0 | E54: 0 | F54: 2 | G54: 1 | H54: 1
C55: Buffers | D55: 0 | E55: 2 | F55: 0 | G55: 0 | H55: 0
B56: Chemical Reactions | C56: Stoichiometry | D56: 0 | E56: 1 | F56: 1 | G56: 0 | H56: 0
C57: Molarity, Normality and Molality | D57: 0 | E57: 7 | F57: 2 | G57: 0 | H57: 0
C58: Equilibrium | D58: 0 | E58: 3 | F58: 0 | G58: 0 | H58: 0
C59: Bioconversion | D59: 0 | E59: 2 | F59: 0 | G59: 0 | H59: 0
A60: Measurements, Instrumentation and Controls | B60: Sensors and Transducers | C60: LVDT | D60: 1 | E60: 3 | F60: 0 | G60: 0 | H60: 0
C61: RTD | D61: 0 | E61: 2 | F61: 1 | G61: 0 | H61: 0
C62: Thermocouple | D62: 0 | E62: 2 | F62: 0 | G62: 0 | H62: 0
C63: Thermistors | D63: 0 | E63: 5 | F63: 2 | G63: 0 | H63: 0
C64: Strain Gage | D64: 0 | E64: 4 | F64: 1 | G64: 0 | H64: 0
C65: Wheatstone Bridge | D65: 0 | E65: 4 | F65: 1 | G65: 0 | H65: 0
C66: Piezoelectric Transducers | D66: 0 | E66: 2 | F66: 0 | G66: 0 | H66: 0
C67: Pressure Sensors | D67: 0 | E67: 2 | F67: 0 | G67: 0 | H67: 0
C68: pH Sensor | D68: 0 | E68: 2 | F68: 0 | G68: 0 | H68: 0
B69: Data Acquistion | C69: Control System | D69: 0 | E69: 6 | F69: 1 | G69: 0 | H69: 0
C70: Logging | D70: 0 | E70: 2 | F70: 2 | G70: 0 | H70: 0
C71: Aliasing | D71: 0 | E71: 1 | F71: 1 | G71: 0 | H71: 0
C72: Nyquist Theorem | D72: 0 | E72: 1 | F72: 3 | G72: 0 | H72: 0
C73: Analog Filters | D73: 0 | E73: 4 | F73: 2 | G73: 0 | H73: 0
C74: Amplification | D74: 0 | E74: 4 | F74: 0 | G74: 0 | H74: 0
C75: Signal Interface | D75: 0 | E75: 1 | F75: 0 | G75: 0 | H75: 0
C76: Signal Processing | D76: 0 | E76: 0 | F76: 0 | G76: 0 | H76: 0
C77: A/D Converters | D77: 0 | E77: 0 | F77: 3 | G77: 0 | H77: 0
C78: D/A Converters | D78: 0 | E78: 0 | F78: 3 | G78: 0 | H78: 0
B79: Logic Diagrams | C79: Logic Gates | D79: 1 | E79: 11 | F79: 1 | G79: 0 | H79: 0
C80: Flowchart | D80: 1 | E80: 4 | F80: 0 | G80: 0 | H80: 1
C81: Pseudocode | D81: 0 | E81: 5 | F81: 2 | G81: 0 | H81: 0
A82: Ethics and Professional Practice | B82: Codes of Ethics | C82: NCEES Model Law | D82: 0 | E82: 11 | F82: 0 | G82: 0 | H82: 0
C83: Ethical and Legal Considerations | D83: 0 | E83: 18 | F83: 0 | G83: 0 | H83: 0
B84: Public Health, Safety and Welfare | C84: Public Health, Safety and Welfare in Engineering | D84: 0 | E84: 5 | F84: 0 | G84: 0 | H84: 0
B85: Societal Considerations | C85: Life Cycle Assessment (LCA) | D85: 1 | E85: 4 | F85: 0 | G85: 0 | H85: 0
C86: Sustainability | D86: 0 | E86: 2 | F86: 0 | G86: 0 | H86: 0
A87: Safety, Health and Environment | B87: Industrial Hygiene | C87: Carcinogens | D87: 0 | E87: 1 | F87: 0 | G87: 0 | H87: 0
C88: Toxicology | D88: 0 | E88: 3 | F88: 0 | G88: 0 | H88: 0
C89: Exposure Limits | D89: 0 | E89: 2 | F89: 0 | G89: 0 | H89: 0
C90: Radiation Exposure | D90: 0 | E90: 2 | F90: 0 | G90: 0 | H90: 0
C91: Biohazards | D91: 0 | E91: 1 | F91: 0 | G91: 0 | H91: 0
C92: Half Life | D92: 0 | E92: 1 | F92: 0 | G92: 0 | H92: 0
B93: Basic Safety Equipment | C93: Pressure-Relief Valves | D93: 1 | E93: 1 | F93: 0 | G93: 0 | H93: 0
C94: Emergency Shutoffs | D94: 0 | E94: 1 | F94: 0 | G94: 0 | H94: 0
C95: Fire Prevention and Control | D95: 0 | E95: 14 | F95: 0 | G95: 0 | H95: 0
C96: Personal Protective Equipment | D96: 0 | E96: 1 | F96: 0 | G96: 0 | H96: 0
B97: Gas Detection and Monitoring | C97: Gas Detection and Monitoring | D97: 0 | E97: 2 | F97: 0 | G97: 0 | H97: 0
B98: Electrical Safety | C98: Electromechanical Components | D98: 0 | E98: 7 | F98: 0 | G98: 0 | H98: 0
C99: Effect of Electrical Current on Human Body | D99: 0 | E99: 2 | F99: 0 | G99: 0 | H99: 0
B100: Confined Space Entry and Ventilation Rates | C100: Confined Space Entry | D100: 0 | E100: 2 | F100: 0 | G100: 0 | H100: 0
C101: Ventilation Rates | D101: 0 | E101: 1 | F101: 0 | G101: 0 | H101: 0
...

Sheet Civil
A1: ENGG.tv Contents
A3: Subject | B3: Chapters | C3: Topics | D3: Video Notes | E3: Theory Questions | F3: Numericals | G3: Vid Explanation | H3: Homework/Solution
A4: Mathematics and Statistics | B4: Math Basics | C4: Logarithms | D4: 0 | E4: 2 | F4: 3 | G4: 0 | H4: 1
C5: Areas and Volumes | D5: 0 | E5: 0 | F5: 4 | G5: 0 | H5: 1
C6: Calculators | D6: 0 | E6: 0 | F6: 2 | G6: 0 | H6: 0
B7: Analytic Geometry | C7: Straight Lines | D7: 1 | E7: 6 | F7: 8 | G7: 3 | H7: 1
C8: Conics | D8: 1 | E8: 2 | F8: 3 | G8: 0 | H8: 0
C9: Circle | D9: 2 | E9: 2 | F9: 14 | G9: 2 | H9: 1
C10: Ellipse | D10: 1 | E10: 2 | F10: 5 | G10: 1 | H10: 1
C11: Parabola | D11: 1 | E11: 2 | F11: 8 | G11: 0 | H11: 1
C12: Hyperbola | D12: 1 | E12: 2 | F12: 7 | G12: 1 | H12: 1
B13: Single-Variable Calculus | C13: Limits | D13: 0 | E13: 2 | F13: 2 | G13: 0 | H13: 1
C14: Derivative | D14: 1 | E14: 4 | F14: 0 | G14: 0 | H14: 1
C15: Application of Derivatives | D15: 0 | E15: 3 | F15: 0 | G15: 0 | H15: 1
C16: Indefinite Integrals | D16: 1 | E16: 0 | F16: 6 | G16: 0 | H16: 0
C17: Definite Integrals | D17: 1 | E17: 5 | F17: 0 | G17: 0 | H17: 1
B18: Vector Operations | C18: Unit Vector | D18: 1 | E18: 4 | F18: 5 | G18: 0 | H18: 0
C19: Dot and Cross Products | D19: 2 | E19: 10 | F19: 0 | G19: 1 | H19: 0
B20: Statistics | C20: Probability- Basic Concepts | D20: 2 | E20: 8 | F20: 0 | G20: 0 | H20: 1
C21: Binomial Distribution | D21: 1 | E21: 6 | F21: 0 | G21: 1 | H21: 1
C22: Normal Distribution | D22: 0 | E22: 4 | F22: 0 | G22: 0 | H22: 1
C23: t-distribution | D23: 0 | E23: 4 | F23: 0 | G23: 0 | H23: 0
C24: Mean, Median, Mode | D24: 0 | E24: 6 | F24: 0 | G24: 0 | H24: 1
C25: Standard Deviation and Variance | D25: 0 | E25: 4 | F25: 0 | G25: 0 | H25: 0
C26: Regression and Curve Fitting | D26: 1 | E26: 8 | F26: 0 | G26: 0 | H26: 0
A27: Ethics and Professional Practice | B27: Codes of Ethics | C27: NCEES Model Law | D27: 0 | E27: 11 | F27: 0 | G27: 0 | H27: 0
C28: Professional and Technical Societies | D28: 0 | E28: 6 | F28: 0 | G28: 0 | H28: 0
C29: Ethical and Legal Considerations | D29: 0 | E29: 18 | F29: 0 | G29: 0 | H29: 0
B30: Public Health, Safety and Welfare | C30: Public Health, Safety and Welfare in Engineering | D30: 0 | E30: 5 | F30: 0 | G30: 0 | H30: 0
B31: Licensure | C31: Licensure | D31: 1 | E31: 1 | F31: 0 | G31: 0 | H31: 0
B32: Contracts and Contract Law | C32: Agreements and Contract | D32: 0 | E32: 4 | F32: 0 | G32: 0 | H32: 0
A33: Engineering Economics | B33: Time Value of Money | C33: Time Value of Money | D33: 1 | E33: 2 | F33: 7 | G33: 1 | H33: 1
B34: Non-Annual Compounding | C34: Non-Annual Compounding | D34: 0 | E34: 2 | F34: 3 | G34: 0 | H34: 1
B35: Break-Even Analysis | C35: Break-Even Analysis | D35: 1 | E35: 11 | F35: 3 | G35: 0 | H35: 0
B36: Inflation | C36: Inflation | D36: 0 | E36: 3 | F36: 2 | G36: 0 | H36: 0
B37: Depreciation | C37: Depreciation | D37: 1 | E37: 3 | F37: 6 | G37: 0 | H37: 0
B38: Capitalized Cost | C38: Capitalized Cost | D38: 0 | E38: 3 | F38: 2 | G38: 0 | H38: 1
B39: Rate of Return | C39: Internal Rate of Return | D39: 0 | E39: 3 | F39: 3 | G39: 0 | H39: 0
B40: Benefit-Cost Analysis | C40: Benefit-Cost Analysis | D40: 0 | E40: 2 | F40: 2 | G40: 0 | H40: 0
B41: Decision Trees | C41: Decision Trees | D41: 0 | E41: 4 | F41: 2 | G41: 0 | H41: 0
B42: Sustainability | C42: Sustainability | D42: 0 | E42: 2 | F42: 0 | G42: 0 | H42: 0
B43: LCA (Life Cycle Assessment) | C43: Life Cycle Assessment (LCA) | D43: 1 | E43: 4 | F43: 0 | G43: 0 | H43: 0
B44: Alternative Energy Sources | C44: Alternative Energy Sources | D44: 0 | E44: 1 | F44: 0 | G44: 0 | H44: 0
B45: Uncertainty | C45: Expected Value | D45: 0 | E45: 2 | F45: 4 | G45: 0 | H45: 0
C46: Risk Terminology | D46: 0 | E46: 4 | F46: 0 | G46: 0 | H46: 0
C47: Types of Risks | D47: 0 | E47: 4 | F47: 0 | G47: 0 | H47: 0
C48: Risk Assessment | D48: 0 | E48: 3 | F48: 0 | G48: 0 | H48: 0
A49: Statics | B49: Resultant of Force Systems | C49: Resolution of Forces | D49: 0 | E49: 5 | F49: 0 | G49: 0 | H49: 0
C50: Resultant of Forces | D50: 1 | E50: 16 | F50: 0 | G50: 0 | H50: 1
C51: Couple | D51: 0 | E51: 5 | F51: 0 | G51: 0 | H51: 0
B52: Concurrent Force Systems | C52: Types of Loads | D52: 0 | E52: 2 | F52: 0 | G52: 0 | H52: 0
C53: Free Body Diagram | D53: 0 | E53: 2 | F53: 0 | G53: 0 | H53: 0
B54: Equilibrium of Rigid Bodies | C54: Types of Supports | D54: 0 | E54: 1 | F54: 0 | G54: 0 | H54: 0
C55: Condition for Static Equilibrium | D55: 0 | E55: 2 | F55: 0 | G55: 0 | H55: 0
C56: Lami’s Theorem | D56: 0 | E56: 4 | F56: 0 | G56: 0 | H56: 0
B57: Frames and Trusses | C57: Method of Joints | D57: 0 | E57: 1 | F57: 0 | G57: 0 | H57: 0
C58: Method of Section | D58: 0 | E58: 1 | F58: 0 | G58: 0 | H58: 0
B59: Centroids of Area | C59: Centroid of Masses, Areas, Lengths and Volumes | D59: 0 | E59: 7 | F59: 0 | G59: 0 | H59: 0
B60: Area Moments of Inertia | C60: Area Moment of Inertia | D60: 0 | E60: 4 | F60: 0 | G60: 1 | H60: 0
C61: Perpendicular Axis Theorem | D61: 0 | E61: 1 | F61: 0 | G61: 0 | H61: 0
C62: Parallel Axis Theorem (Statics) | D62: 0 | E62: 4 | F62: 0 | G62: 0 | H62: 0
C63: Radius of Gyration | D63: 0 | E63: 1 | F63: 0 | G63: 0 | H63: 0
C64: Product of Inertia | D64: 0 | E64: 1 | F64: 0 | G64: 0 | H64: 0
B65: Static Friction | C65: Static Friction | D65: 0 | E65: 20 | F65: 0 | G65: 0 | H65: 0
C66: Screw Thread | D66: 0 | E66: 3 | F66: 0 | G66: 0 | H66: 0
C67: Belt Friction | D67: 0 | E67: 4 | F67: 0 | G67: 0 | H67: 0
A68: Dynamics | B68: Kinematics | C68: Instantaneous Velocity and Acceleration | D68: 0 | E68: 3 | F68: 4 | G68: 0 | H68: 1
C69: Tangential and Normal Component of Acceleration | D69: 1 | E69: 3 | F69: 4 | G69: 0 | H69: 0
C70: Constant Acceleration Motion | D70: 1 | E70: 2 | F70: 10 | G70: 0 | H70: 0
C71: Variable Acceleration Motion | D71: 1 | E71: 1 | F71: 3 | G71: 0 | H71: 0
C72: Relative Motion | D72: 1 | E72: 1 | F72: 2 | G72: 0 | H72: 0
C73: Uniform Circular Motion | D73: 0 | E73: 2 | F73: 3 | G73: 1 | H73: 0
C74: Projectile Motion | D74: 1 | E74: 2 | F74: 5 | G74: 0 | H74: 1
C75: General Rotation of a Rigid Body | D75: 0 | E75: 4 | F75: 1 | G75: 0 | H75: 0
C76: Rotation of Rigid Body under Constant Acceleration | D76: 0 | E76: 0 | F76: 2 | G76: 0 | H76: 0
C77: Rotation of Rigid Body under Variable Acceleration | D77: 0 | E77: 0 | F77: 1 | G77: 0 | H77: 0
C78: Instantaneous Center of Rotation | D78: 0 | E78: 6 | F78: 2 | G78: 0 | H78: 0
B79: Mass Moment of Inertia | C79: Moment of Inertia of a Point Mass | D79: 1 | E79: 4 | F79: 0 | G79: 0 | H79: 0
C80: Mass Moment of Inertia of a Rigid Body | D80: 1 | E80: 4 | F80: 0 | G80: 0 | H80: 0
C81: Mass Radius of Gyration | D81: 0 | E81: 1 | F81: 2 | G81: 0 | H81: 0
C82: Parallel Axes Theorem- Dynamics | D82: 0 | E82: 8 | F82: 2 | G82: 0 | H82: 0
B83: Force Acceleration | C83: One-Dimensional Motion of a Particle | D83: 0 | E83: 0 | F83: 2 | G83: 0 | H83: 0
C84: One-Dimensional Motion of a Rigid Body | D84: 1 | E84: 0 | F84: 2 | G84: 0 | H84: 0
C85: Kinetic Friction | D85: 0 | E85: 2 | F85: 3 | G85: 0 | H85: 0
B86: Work, Energy and Power | C86: Kinetic Energy | D86: 0 | E86: 2 | F86: 2 | G86: 0 | H86: 1
C87: Potential Energy | D87: 1 | E87: 3 | F87: 2 | G87: 0 | H87: 0
C88: Work | D88: 1 | E88: 2 | F88: 4 | G88: 0 | H88: 0
C89: Power and Efficiency | D89: 0 | E89: 1 | F89: 3 | G89: 0 | H89: 0
C90: Law of Conservation of Energy | D90: 0 | E90: 3 | F90: 0 | G90: 0 | H90: 0
C91: Kinetic Energy of a Rigid Body | D91: 0 | E91: 3 | F91: 4 | G91: 0 | H91: 0
A92: Mechanics of Materials | B92: Uniaxial Stress-Strain | C92: Stress and Strain | D92: 0 | E92: 2 | F92: 2 | G92: 0 | H92: 0
C93: Poisson’s Ratio | D93: 0 | E93: 11 | F93: 3 | G93: 0 | H93: 0
C94: Percentage Changes | D94: 0 | E94: 1 | F94: 0 | G94: 0 | H94: 0
C95: Shear Stress- Strain | D95: 0 | E95: 30 | F95: 3 | G95: 0 | H95: 0
C96: Moduli of Elasticity | D96: 0 | E96: 3 | F96: 6 | G96: 0 | H96: 0
B97: Thermal Deformations | C97: Thermal Deformations | D97: 1 | E97: 2 | F97: 2 | G97: 0 | H97: 0
B98: Two Dimensional Stress and Strain | C98: Principal Stresses | D98: 0 | E98: 1 | F98: 3 | G98: 0 | H98: 1
C99: Mohr’s Circle | D99: 1 | E99: 2 | F99: 2 | G99: 0 | H99: 0
B100: Hooke’s Law | C100: Hooke’s Law | D100: 0 | E100: 1 | F100: 1 | G100: 0 | H100: 0
B101: Torsion | C101: Solid, Thick Walled Shafts | D101: 0 | E101: 0 | F101: 2 | G101: 0 | H101: 0
...

Sheet Summary
B2: ENGG.tv Status for Various Disciplines (As on May 15, 2024)
C3: Civil | D3: Other | E3: Mechanical
B4: Chapters | C4: ='Civil'!J267 -> 73 | D4: ='Other'!J323 -> 95 | E4: ='Mechanical'!J369 -> 117
B5: Topics | C5: ='Civil'!K267 -> 245 | D5: ='Other'!K323 -> 301 | E5: ='Mechanical'!K369 -> 339
B6: Video Notes | C6: ='Civil'!L267 -> 41 | D6: ='Other'!L323 -> 79 | E6: ='Mechanical'!L369 -> 94
B7: Theory Questions | C7: ='Civil'!M267 -> 971 | D7: ='Other'!M323 -> 1202 | E7: ='Mechanical'!M369 -> 1770
B8: Numericals | C8: ='Civil'!N267 -> 378 | D8: ='Other'!N323 -> 691 | E8: ='Mechanical'!N369 -> 844
B9: Vid Explanation | C9: ='Civil'!O267 -> 16 | D9: ='Other'!O323 -> 26 | E9: ='Mechanical'!O369 -> 30
B10: Homework/Solution | C10: ='Civil'!P267 -> 29 | D10: ='Other'!P323 -> 43 | E10: ='Mechanical'!P369 -> 50
B11: Sample Test with Solutions | C11: Yes | D11: Yes | E11: Yes

Sheet Electrical and Computer
A1: ENGG.tv Contents
A3: Subject | B3: Chapters | C3: Topics | D3: Video Notes | E3: Solved Examples | F3: Vid Explanation | G3: Homework/Solution
A4: Mathematics | B4: Math Basics | C4: Logarithms | D4: 0 | E4: 3 | F4: 0 | G4: 1
C5: Areas and Volumes | D5: 0 | E5: 3 | F5: 0 | G5: 0
C6: Calculators | D6: 0 | E6: 2 | F6: 0 | G6: 0
B7: Algebra and Trigonometry | C7: Algebraic Equations and Roots | D7: 0 | E7: 4 | F7: 0 | G7: 0
C8: Trigonometry | D8: 3 | E8: 2 | F8: 0 | G8: 0
B9: Complex Numbers | C9: Theory of Complex Numbers | D9: 0 | E9: 2 | F9: 0 | G9: 0
C10: Different Forms of Complex Numbers | D10: 0 | E10: 2 | F10: 0 | G10: 1
C11: Algebraic Operations on Complex Numbers | D11: 1 | E11: 1 | F11: 0 | G11: 0
C12: De Moiver’s Theorem | D12: 0 | E12: 2 | F12: 0 | G12: 0
C13: Roots of Complex Number | D13: 0 | E13: 2 | F13: 0 | G13: 1
B14: Discrete Mathematics | C14: Terminology and Symbols | D14: 0 | E14: 3 | F14: 0 | G14: 0
C15: Matrix of Relations | D15: 0 | E15: 1 | F15: 0 | G15: 0
C16: Diagraph | D16: 0 | E16: 1 | F16: 0 | G16: 0
B17: Analytic Geometry | C17: Straight Lines | D17: 1 | E17: 8 | F17: 3 | G17: 1
C18: Conics | D18: 3 | E18: 3 | F18: 0 | G18: 0
C19: Circles | D19: 2 | E19: 15 | F19: 2 | G19: 1
C20: Ellipse | D20: 1 | E20: 9 | F20: 1 | G20: 1
C21: Parabola | D21: 1 | E21: 10 | F21: 0 | G21: 1
C22: Hyperbola | D22: 1 | E22: 6 | F22: 1 | G22: 1
C23: Distance Formula | D23: 0 | E23: 2 | F23: 0 | G23: 1
B24: Calculus | C24: Limits | D24: 1 | E24: 14 | F24: 1 | G24: 1
C25: Derivative | D25: 1 | E25: 4 | F25: 0 | G25: 1
C26: Application of Derivatives | D26: 2 | E26: 3 | F26: 0 | G26: 1
C27: Partial Derivatives | D27: 0 | E27: 4 | F27: 1 | G27: 1
C28: Indefinite Integrals | D28: 0 | E28: 3 | F28: 0 | G28: 0
C29: Partial Fractions | D29: 1 | E29: 2 | F29: 0 | G29: 0
C30: Trigonometric Functions | D30: 0 | E30: 2 | F30: 0 | G30: 1
C31: Definite Integrals | D31: 1 | E31: 5 | F31: 0 | G31: 1
B32: Ordinary Differential Equations | C32: General Terminology | D32: 1 | E32: 3 | F32: 0 | G32: 0
C33: First Order DE | D33: 1 | E33: 10 | F33: 0 | G33: 0
C34: Second Order Homogeneous DE | D34: 2 | E34: 3 | F34: 1 | G34: 0
C35: Finding Differential Equation from Solution | D35: 0 | E35: 7 | F35: 0 | G35: 0
C36: Applying Boundary Conditions | D36: 0 | E36: 11 | F36: 1 | G36: 0
C37: Laplace Transform | D37: 1 | E37: 10 | F37: 1 | G37: 1
B38: Linear Algebra | C38: Types of Matrices | D38: 1 | E38: 2 | F38: 0 | G38: 0
C39: Determinant of a Matrix | D39: 0 | E39: 1 | F39: 0 | G39: 0
C40: Matrix Operations | D40: 0 | E40: 8 | F40: 0 | G40: 0
B41: Vector Analysis | C41: Unit Vector | D41: 1 | E41: 2 | F41: 0 | G41: 0
C42: Addition and Subtraction of Vectors | D42: 0 | E42: 1 | F42: 0 | G42: 0
C43: Dot and Cross Products | D43: 2 | E43: 10 | F43: 1 | G43: 0
C44: Gradient, Divergence and Curl | D44: 1 | E44: 14 | F44: 0 | G44: 1
A45: Probability and Statistics | B45: Measures of Central Tendencies and Distribution | C45: Mean, Median Mode | D45: 1 | E45: 6 | F45: 0 | G45: 1
C46: Standard Deviation and Variance | D46: 0 | E46: 4 | F46: 0 | G46: 0
B47: Probability Distributions | C47: Probability- Basic Concepts | D47: 2 | E47: 8 | F47: 0 | G47: 1
C48: Binomial Distribution | D48: 1 | E48: 6 | F48: 1 | G48: 1
C49: Normal Distribution | D49: 1 | E49: 4 | F49: 0 | G49: 1
C50: t-distribution | D50: 1 | E50: 4 | F50: 0 | G50: 0
C51: Chi-squared distribution | D51: 2 | E51: 5 | F51: 0 | G51: 0
B52: Expected Value | C52: PDF and CDF | D52: 1 | E52: 1 | F52: 1 | G52: 0
C53: Expected Value | D53: 0 | E53: 4 | F53: 0 | G53: 0
A54: Ethics and Professional Practice | B54: Codes of Ethics | C54: NCEES Model Law | D54: 0 | E54: 11 | F54: 0 | G54: 0
C55: Professional and Technical Societies | D55: 0 | E55: 1 | F55: 0 | G55: 0
C56: Ethical and Legal Considerations | D56: 0 | E56: 18 | F56: 0 | G56: 0
B57: Intellectual Property | C57: Introduction to Intellectual Property | D57: 0 | E57: 2 | F57: 0 | G57: 0
C58: Patents and Copyrights | D58: 0 | E58: 3 | F58: 0 | G58: 0
C59: Trademarks | D59: 0 | E59: 2 | F59: 0 | G59: 0
C60: Trade Secrets | D60: 0 | E60: 2 | F60: 0 | G60: 0
B61: Public Health, Safety and Welfare | C61: Public Health, Safety and Welfare in Engineering | D61: 0 | E61: 2 | F61: 0 | G61: 0
A62: Engineering Economics | B62: Time Value of Money | C62: Discounted Cash Flow Factors | D62: 1 | E62: 5 | F62: 1 | G62: 1
C63: Net Present Value | D63: 0 | E63: 3 | F63: 0 | G63: 1
C64: Inflation | D64: 0 | E64: 3 | F64: 0 | G64: 0
B65: Cost Types and Breakdowns | C65: Cost Types | D65: 0 | E65: 3 | F65: 0 | G65: 0
B66: Risk Identification | C66: Risk Terminology | D66: 0 | E66: 2 | F66: 0 | G66: 0
C67: Types of Risks | D67: 0 | E67: 4 | F67: 0 | G67: 0
C68: Risk Assessment | D68: 0 | E68: 3 | F68: 0 | G68: 0
B69: Economic Analyses | C69: Payback Period Analysis | D69: 0 | E69: 3 | F69: 0 | G69: 0
C70: Cost-Benefit Analysis | D70: 0 | E70: 2 | F70: 1 | G70: 0
C71: Break-Even Analysis | D71: 1 | E71: 14 | F71: 1 | G71: 1
C72: Overhead Analysis | D72: 0 | E72: 1 | F72: 0 | G72: 0
A73: Properties of Materials | B73: Semiconductor | C73: Tunneling | D73: 0 | E73: 4 | F73: 0 | G73: 0
C74: Diffusion/Drift Current | D74: 0 | E74: 4 | F74: 0 | G74: 0
C75: Energy Bands | D75: 0 | E75: 5 | F75: 0 | G75: 0
C76: Doping Bands | D76: 0 | E76: 3 | F76: 0 | G76: 0
C77: P-N Theory | D77: 0 | E77: 7 | F77: 0 | G77: 0
B78: Electrical | C78: Conductivity | D78: 0 | E78: 3 | F78: 0 | G78: 0
C79: Resistivity | D79: 0 | E79: 1 | F79: 0 | G79: 0
C80: Permittivity | D80: 0 | E80: 2 | F80: 0 | G80: 0
C81: Permeability | D81: 0 | E81: 2 | F81: 0 | G81: 0
C82: Noise | D82: 0 | E82: 7 | F82: 0 | G82: 0
B83: Thermal | C83: Thermal Conductivity | D83: 0 | E83: 1 | F83: 0 | G83: 0
C84: Thermal Expansion | D84: 0 | E84: 5 | F84: 0 | G84: 0
A85: Circuit Analysis | B85: KCL, KVL | C85: Kirchhoff’s Laws | D85: 0 | E85: 12 | F85: 0 | G85: 0
B86: Series/Parallel Circuits | C86: Resistances in Series | D86: 0 | E86: 2 | F86: 0 | G86: 0
C87: Resistances in Parallel | D87: 0 | E87: 7 | F87: 0 | G87: 0
B88: Thevenin/Norton | C88: Thevenin Theorem | D88: 0 | E88: 1 | F88: 0 | G88: 0
C89: Norton Theorem | D89: 0 | E89: 4 | F89: 0 | G89: 0
B90: Node/Loop Analysis | C90: Nodal Analysis | D90: 0 | E90: 3 | F90: 0 | G90: 0
C91: Mesh Analysis | D91: 0 | E91: 6 | F91: 0 | G91: 0
B92: Waveform Analysis | C92: RMS Value | D92: 1 | E92: 5 | F92: 0 | G92: 0
C93: Average Value | D93: 0 | E93: 2 | F93: 0 | G93: 1
C94: Frequency | D94: 0 | E94: 0 | F94: 0 | G94: 0
C95: Phase | D95: 0 | E95: 2 | F95: 0 | G95: 0
C96: Wavelength | D96: 0 | E96: 0 | F96: 0 | G96: 0
B97: Phasors | C97: Phasors in Pure RLC Circuits | D97: 0 | E97: 5 | F97: 0 | G97: 0
C98: Phasors of Mixed Circuits | D98: 0 | E98: 2 | F98: 0 | G98: 0
B99: Impedance | C99: AC Impedance | D99: 1 | E99: 12 | F99: 0 | G99: 1
A100: Linear Systems | B100: Frequency/Transient Response | C100: Transient Response | D100: 0 | E100: 10 | F100: 0 | G100: 0
B101: Resonance | C101: Resonance | D101: 0 | E101: 5 | F101: 0 | G101: 0
...

Sheet Chemical
A1: ENGG.tv Contents
A3: Subject | B3: Chapters | C3: Topics | D3: Video Notes | E3: Solved Examples | F3: Vid Explanation | G3: Homework/Solution
A4: Mathematics | B4: Analytic Geometry | C4: Straight Lines | D4: 1 | E4: 13 | F4: 3 | G4: 1
C5: Conics | D5: 0 | E5: 3 | F5: 0 | G5: 0
C6: Circles | D6: 2 | E6: 15 | F6: 2 | G6: 1
C7: Ellipse | D7: 1 | E7: 9 | F7: 1 | G7: 1
C8: Parabola | D8: 1 | E8: 10 | F8: 0 | G8: 1
C9: Hyperbola | D9: 1 | E9: 6 | F9: 1 | G9: 1
C10: Distance Formula | D10: 0 | E10: 2 | F10: 0 | G10: 1
B11: Calculus | C11: Limits | D11: 0 | E11: 14 | F11: 1 | G11: 1
C12: Derivative | D12: 1 | E12: 4 | F12: 0 | G12: 1
C13: Application of Derivatives | D13: 0 | E13: 3 | F13: 0 | G13: 1
C14: Partial Derivatives | D14: 0 | E14: 4 | F14: 1 | G14: 1
C15: Indefinite Integrals | D15: 0 | E15: 3 | F15: 0 | G15: 0
C16: Partial Fractions | D16: 1 | E16: 2 | F16: 0 | G16: 0
C17: Trigonometric Functions | D17: 0 | E17: 2 | F17: 0 | G17: 1
C18: Definite Integrals | D18: 1 | E18: 5 | F18: 0 | G18: 1
B19: Differential Equations | C19: General Terminology | D19: 1 | E19: 3 | F19: 0 | G19: 0
C20: First Order DE | D20: 1 | E20: 10 | F20: 0 | G20: 0
C21: Second Order Homogeneous DE | D21: 2 | E21: 3 | F21: 1 | G21: 0
C22: Finding Differential Equation from Solution | D22: 0 | E22: 7 | F22: 0 | G22: 0
C23: Applying Boundary Conditions | D23: 0 | E23: 11 | F23: 1 | G23: 0
C24: Laplace Transform | D24: 1 | E24: 10 | F24: 1 | G24: 1
B25: Linear Algebra | C25: Types of Matrices | D25: 0 | E25: 2 | F25: 0 | G25: 0
C26: Determinant of a Matrix | D26: 0 | E26: 1 | F26: 0 | G26: 0
C27: Matrix Operations | D27: 0 | E27: 8 | F27: 0 | G27: 0
C28: Unit Vector | D28: 0 | E28: 2 | F28: 0 | G28: 0
C29: Addition and Subtraction of Vectors | D29: 0 | E29: 1 | F29: 0 | G29: 0
C30: Dot and Cross Products | D30: 2 | E30: 10 | F30: 1 | G30: 0
C31: Gradient, Divergence and Curl | D31: 1 | E31: 14 | F31: 0 | G31: 1
B32: Numerical Methods | C32: Newton’s Method of Root Extraction | D32: 0 | E32: 4 | F32: 0 | G32: 1
C33: Newton’s Method of Minimization | D33: 0 | E33: 2 | F33: 0 | G33: 0
C34: Forward Rectangle Rule | D34: 0 | E34: 1 | F34: 0 | G34: 1
C35: Trapezoidal Rule | D35: 1 | E35: 5 | F35: 1 | G35: 1
C36: Simpson’s Rule | D36: 0 | E36: 2 | F36: 0 | G36: 0
C37: Taylor’s and McLaurin’s Series | D37: 0 | E37: 2 | F37: 0 | G37: 1
B38: Algorithm and Logic Development | C38: Flowchart | D38: 1 | E38: 1 | F38: 0 | G38: 1
C39: Key Terms in Flowchart and Programming | D39: 0 | E39: 5 | F39: 0 | G39: 0
C40: Pseudocode | D40: 0 | E40: 5 | F40: 0 | G40: 0
A41: Probability and Statistics | B41: Probability Distributions | C41: Probability- Basic Concepts | D41: 2 | E41: 8 | F41: 0 | G41: 1
C42: Binomial Distribution | D42: 1 | E42: 6 | F42: 1 | G42: 1
C43: Normal Distribution | D43: 0 | E43: 4 | F43: 0 | G43: 1
C44: t-distribution | D44: 0 | E44: 4 | F44: 0 | G44: 0
C45: Chi-squared distribution | D45: 2 | E45: 5 | F45: 0 | G45: 0
B46: Measures of Central Tendencies and Distribution | C46: Mean, Median Mode | D46: 0 | E46: 6 | F46: 0 | G46: 1
C47: Standard Deviation and Variance | D47: 0 | E47: 4 | F47: 0 | G47: 0
B48: Expected Value | C48: PDF and CDF | D48: 0 | E48: 1 | F48: 1 | G48: 0
C49: Expected Value | D49: 0 | E49: 4 | F49: 0 | G49: 0
B50: Regression, Curve Fitting, Goodness of Fit | C50: Regression and Curve Fitting | D50: 1 | E50: 8 | F50: 0 | G50: 0
A51: Engineering Science | B51: Basic Dynamics | C51: Kinetic Friction | D51: 0 | E51: 5 | F51: 0 | G51: 0
C52: Instant. Velocity and Acceleration | D52: 0 | E52: 7 | F52: 0 | G52: 1
C53: Normal and Tangential Acceleration | D53: 0 | E53: 6 | F53: 0 | G53: 0
C54: Constant Acceleration | D54: 1 | E54: 10 | F54: 0 | G54: 0
C55: Linear and Angular Momentum | D55: 0 | E55: 1 | F55: 0 | G55: 0
B56: Work, Energy, and Power | C56: Kinetic Energy | D56: 0 | E56: 4 | F56: 0 | G56: 1
C57: Potential Energy | D57: 0 | E57: 4 | F57: 0 | G57: 0
C58: Work | D58: 0 | E58: 2 | F58: 0 | G58: 0
C59: Power and Efficiency | D59: 0 | E59: 1 | F59: 0 | G59: 0
C60: Law of Conservation of Energy | D60: 0 | E60: 3 | F60: 0 | G60: 0
B61: Electricity, Current, and Voltage Laws | C61: Coulomb’s Law | D61: 0 | E61: 7 | F61: 0 | G61: 1
C62: Electric Current | D62: 0 | E62: 2 | F62: 0 | G62: 1
C63: Resistance | D63: 0 | E63: 7 | F63: 0 | G63: 0
C64: Electric Power | D64: 0 | E64: 4 | F64: 0 | G64: 0
C65: Kirchhoff’s Laws | D65: 0 | E65: 12 | F65: 0 | G65: 0
C66: Resistance in Series | D66: 0 | E66: 2 | F66: 0 | G66: 0
C67: Resistances in Parallel | D67: 0 | E67: 7 | F67: 1 | G67: 0
A68: Material Science | B68: Properties | C68: Chemical | D68: 0 | E68: 4 | F68: 0 | G68: 0
C69: Mechanical | D69: 0 | E69: 17 | F69: 0 | G69: 0
C70: Electrical | D70: 0 | E70: 2 | F70: 0 | G70: 0
C71: Thermal | D71: 0 | E71: 3 | F71: 0 | G71: 0
B72: Material Types | C72: Ferrous | D72: 0 | E72: 6 | F72: 0 | G72: 0
C73: Non-Ferrous | D73: 0 | E73: 14 | F73: 0 | G73: 0
C74: Engineered Materials | D74: 0 | E74: 17 | F74: 0 | G74: 0
B75: Corrosion Mechanisms and Control | C75: Corrosion Terminology | D75: 0 | E75: 2 | F75: 0 | G75: 0
C76: Corrosion Mechanism | D76: 0 | E76: 3 | F76: 0 | G76: 0
C77: EMF Series | D77: 0 | E77: 3 | F77: 0 | G77: 0
C78: Galvanic Series | D78: 0 | E78: 1 | F78: 0 | G78: 0
C79: Corrosion Control | D79: 0 | E79: 4 | F79: 0 | G79: 0
A80: Chemistry and Biology | B80: Inorganic Chemistry | C80: Molarity | D80: 0 | E80: 1 | F80: 0 | G80: 0
C81: Normality | D81: 0 | E81: 1 | F81: 0 | G81: 0
C82: Molality | D82: 0 | E82: 3 | F82: 0 | G82: 0
C83: Acids and Bases | D83: 0 | E83: 5 | F83: 0 | G83: 0
C84: Redox Reactions | D84: 0 | E84: 2 | F84: 0 | G84: 0
C85: Valence | D85: 0 | E85: 2 | F85: 0 | G85: 0
C86: Solubility Product | D86: 0 | E86: 2 | F86: 0 | G86: 0
C87: pH | D87: 0 | E87: 9 | F87: 0 | G87: 0
C88: pK | D88: 0 | E88: 1 | F88: 0 | G88: 0
C89: Electrochemistry | D89: 0 | E89: 2 | F89: 0 | G89: 0
C90: Periodic Table | D90: 0 | E90: 5 | F90: 0 | G90: 0
B91: Organic Chemistry | C91: Nomenclature | D91: 0 | E91: 5 | F91: 0 | G91: 0
C92: Structure | D92: 0 | E92: 1 | F92: 0 | G92: 0
C93: Balanced Equation | D93: 0 | E93: 1 | F93: 0 | G93: 0
C94: Reaction | D94: 0 | E94: 0 | F94: 0 | G94: 0
C95: Synthesis | D95: 0 | E95: 0 | F95: 0 | G95: 0
B96: Analytical Chemistry | C96: Wet Chemistry | D96: 0 | E96: 3 | F96: 0 | G96: 0
C97: Instrumental Chemistry | D97: 0 | E97: 1 | F97: 0 | G97: 0
B98: Biochemistry, Microbiology, and Molecular Biology | C98: Organization and Function of a Cell | D98: 0 | E98: 2 | F98: 0 | G98: 0
C99: Krebs, Glycolysis, Calvin Cycles | D99: 0 | E99: 5 | F99: 0 | G99: 0
C100: Enzymes and Protein Chemistry | D100: 0 | E100: 12 | F100: 0 | G100: 0
C101: Genetics | D101: 0 | E101: 6 | F101: 0 | G101: 0
...

Sheet Industrial
A1: ENGG.tv Contents
A3: Subject | B3: Chapters | C3: Topics | D3: Video Notes | E3: Solved Examples | F3: Vid Explanation | G3: Homework/Solution
A4: Mathematics | B4: Math Basics | C4: Trigonometry | D4: 2 | E4: 6 | F4: 0 | G4: 2
C5: Logarithms | D5: 0 | E5: 1 | F5: 0 | G5: 3
C6: Theory of Complex Numbers | D6: 0 | E6: 1 | F6: 0 | G6: 2
C7: Calculators | D7: 0 | E7: 0 | F7: 0 | G7: 0
B8: Analytic Geometry | C8: Straight Lines | D8: 1 | E8: 13 | F8: 3 | G8: 1
C9: Conics | D9: 3 | E9: 3 | F9: 0 | G9: 0
C10: Circles | D10: 2 | E10: 15 | F10: 2 | G10: 1
C11: Ellipse | D11: 1 | E11: 9 | F11: 1 | G11: 1
C12: Parabola | D12: 1 | E12: 10 | F12: 0 | G12: 1
C13: Hyperbola | D13: 1 | E13: 6 | F13: 1 | G13: 1
C14: Distance Formula | D14: 0 | E14: 2 | F14: 0 | G14: 1
C15: Area and Volumes | D15: 0 | E15: 3 | F15: 0 | G15: 0
B16: Calculus | C16: Limits | D16: 0 | E16: 14 | F16: 1 | G16: 1
C17: Derivative | D17: 1 | E17: 4 | F17: 0 | G17: 1
C18: Application of Derivatives | D18: 2 | E18: 3 | F18: 0 | G18: 1
C19: Partial Derivatives | D19: 0 | E19: 4 | F19: 1 | G19: 1
C20: Indefinite Integrals | D20: 0 | E20: 3 | F20: 0 | G20: 0
C21: Partial Fractions | D21: 1 | E21: 2 | F21: 0 | G21: 0
C22: Definite Integrals | D22: 1 | E22: 5 | F22: 0 | G22: 1
C23: Progressions | D23: 0 | E23: 6 | F23: 0 | G23: 1
C24: Series | D24: 0 | E24: 2 | F24: 0 | G24: 0
B25: Linear Algebra | C25: Types of Matrices | D25: 0 | E25: 2 | F25: 0 | G25: 0
C26: Determinant of a Matrix | D26: 0 | E26: 1 | F26: 0 | G26: 0
C27: Matrix Operations | D27: 0 | E27: 8 | F27: 0 | G27: 0
C28: Unit Vector | D28: 0 | E28: 2 | F28: 0 | G28: 0
C29: Addition and Subtraction of Vectors | D29: 0 | E29: 1 | F29: 0 | G29: 0
C30: Dot and Cross Products | D30: 2 | E30: 10 | F30: 1 | G30: 0
C31: Gradient, Divergence and Curl | D31: 1 | E31: 14 | F31: 0 | G31: 1
B32: Thermodynamics | C32: Thermodynamic Properties
C33: Ideal Gas Laws
C34: Zeroth Law
C35: First Law
C36: Second Law
C37: Third Law
C38: Thermodynamic Processes
C39: Isochoric Processes
C40: Isobaric Processes
C41: Adiabatic Processes
C42: Polytropic Processes
B43: Fluid Mechanics | C43: Fluid Properties
C44: Newton’s Law of Viscosity
C45: Surface Tension/Capillarity
C46: Pascal’s Law
C47: Pressure Measurement
C48: Reynold’s Number
C49: Pumps
C50: Compressors
A51: Engineering Science | B51: Statics | C51: Static Friction | D51: 0 | E51: 20 | F51: 0 | G51: 0
C52: Kinetic Friction | D52: 0 | E52: 5 | F52: 0 | G52: 0
C53: Instant. Velocity and Acceleration | D53: 0 | E53: 7 | F53: 0 | G53: 1
C54: Normal and Tangential Acceleration | D54: 0 | E54: 6 | F54: 0 | G54: 0
C55: Constant Acceleration | D55: 1 | E55: 10 | F55: 0 | G55: 0
C56: Linear and Angular Momentum | D56: 0 | E56: 1 | F56: 0 | G56: 0
B57: Dynamics | C57: Kinetic Energy | D57: 0 | E57: 4 | F57: 0 | G57: 1
C58: Potential Energy | D58: 0 | E58: 4 | F58: 0 | G58: 0
C59: Work | D59: 0 | E59: 2 | F59: 0 | G59: 0
C60: Power and Efficiency | D60: 0 | E60: 1 | F60: 0 | G60: 0
C61: Law of Conservation of Energy | D61: 0 | E61: 3 | F61: 0 | G61: 0
B62: Electricity and Electrical Circuits | C62: Coulomb’s Law | D62: 0 | E62: 7 | F62: 0 | G62: 1
C63: Electric Current | D63: 0 | E63: 2 | F63: 0 | G63: 1
C64: Resistance | D64: 0 | E64: 7 | F64: 0 | G64: 0
C65: Electric Power | D65: 0 | E65: 4 | F65: 0 | G65: 0
C66: Kirchhoff’s Laws | D66: 0 | E66: 12 | F66: 0 | G66: 0
C67: Resistance in Series | D67: 0 | E67: 2 | F67: 0 | G67: 0
C68: Resistances in Parallel | D68: 0 | E68: 7 | F68: 1 | G68: 0
A69: Ethics and Professional Practice | B69: Codes of Ethics and Licensure | C69: NCEES Model Law | D69: 0 | E69: 11 | F69: 0 | G69: 0
C70: Professional and Technical Societies | D70: 0 | E70: 1 | F70: 0 | G70: 0
C71: Ethical and Legal Considerations | D71: 0 | E71: 18 | F71: 0 | G71: 0
C72: Licensure | D72: 0 | E72: 1 | F72: 0 | G72: 0
B73: Agreements and Contracts | C73: Agreements and Contracts | D73: 0 | E73: 4 | F73: 0 | G73: 0
B74: Public Health, Safety and Welfare | C74: Public Health, Safety and Welfare in Engineering | D74: 0 | E74: 2 | F74: 0 | G74: 0
B75: Public Protection and Regulatory Issues
A77: Engineering Economics | B77: Time Value of Money | C77: Discounted Cash Flow Factors | D77: 1 | E77: 5 | F77: 1 | G77: 1
C78: Inflation | D78: 0 | E78: 3 | F78: 0 | G78: 0
B79: Evaluation of Alternatives | C79: Net Present Value | D79: 0 | E79: 3 | F79: 0 | G79: 1
C80: Payback Period Analysis | D80: 0 | E80: 3 | F80: 0 | G80: 0
C81: Cost-Benefit Analysis | D81: 0 | E81: 2 | F81: 1 | G81: 0
C82: Break-Even Analysis | D82: 1 | E82: 14 | F82: 1 | G82: 1
C83: Overhead Analysis | D83: 0 | E83: 1 | F83: 0 | G83: 0
C84: Equivalent Annual Cost | D84: 0 | E84: 1 | F84: 0 | G84: 0
C85: Internal Rate of Return | D85: 0 | E85: 3 | F85: 0 | G85: 0
B86: Cost Types and Breakdowns | C86: Cost Types | D86: 0 | E86: 3 | F86: 0 | G86: 0
B87: Depreciation and Taxes | C87: Depreciation | D87: 0 | E87: 4 | F87: 1 | G87: 0
C88: After-Tax Cash Flow | D88: 0 | E88: 2 | F88: 0 | G88: 0
C89: Recapture | D89: 0 | E89: 1 | F89: 0 | G89: 0
A90: Probability and Statistics | B90: Probability Distributions | C90: Probability- Basic Concepts | D90: 2 | E90: 8 | F90: 0 | G90: 1
C91: Binomial Distribution | D91: 1 | E91: 6 | F91: 1 | G91: 1
C92: Normal Distribution | D92: 0 | E92: 4 | F92: 0 | G92: 1
C93: t-distribution | D93: 0 | E93: 4 | F93: 0 | G93: 0
C94: Chi-squared distribution | D94: 2 | E94: 5 | F94: 0 | G94: 0
B95: Measures of Central Tendencies and Distribution | C95: Mean, Median Mode | D95: 0 | E95: 6 | F95: 0 | G95: 1
C96: Standard Deviation and Variance | D96: 0 | E96: 4 | F96: 0 | G96: 0
B97: Expected Value | C97: PDF and CDF | D97: 0 | E97: 1 | F97: 1 | G97: 0
C98: Expected Value | D98: 0 | E98: 4 | F98: 0 | G98: 0
B99: Linear Regression | C99: Regression and Curve Fitting | D99: 1 | E99: 8 | F99: 0 | G99: 0
B100: Design of Experiments | C100: ANOVA | D100: 0 | E100: 3 | F100: 0 | G100: 0
C101: Factorial Designs | D101: 0 | E101: 2 | F101: 0 | G101: 0
A102: Modeling and Quantitative Analysis | B102: Data, Logic Development, and Analytics | C102: Database | D102: 0 | E102: 3 | F102: 0 | G102: 0
...

Sheet Environmental
A1: ENGG.tv Contents
A3: Subject | B3: Chapters | C3: Topics | D3: Video Notes | E3: Solved Examples | F3: Vid Explanation | G3: Homework/Solution
A4: Mathematics | B4: Analytic Geometry and Trigonometry | C4: Straight Lines | D4: 1 | E4: 13 | F4: 3 | G4: 1
C5: Conics | D5: 0 | E5: 3 | F5: 0 | G5: 0
C6: Circles | D6: 2 | E6: 15 | F6: 2 | G6: 1
C7: Ellipse | D7: 1 | E7: 9 | F7: 1 | G7: 1
C8: Parabola | D8: 1 | E8: 10 | F8: 0 | G8: 1
C9: Hyperbola | D9: 1 | E9: 6 | F9: 1 | G9: 1
C10: Distance Formula | D10: 0 | E10: 2 | F10: 0 | G10: 1
C11: Trigonometry | D11: 0 | E11: 2 | F11: 0 | G11: 0
B12: Algebraic Equations and Roots | C12: Algebraic Equations and Roots | D12: 0 | E12: 4 | F12: 0 | G12: 0
C13: Newton’s Method of Root Extraction | D13: 0 | E13: 4 | F13: 0 | G13: 1
B14: Calculus | C14: Limits | D14: 0 | E14: 14 | F14: 1 | G14: 1
C15: Derivative | D15: 1 | E15: 4 | F15: 0 | G15: 1
C16: Application of Derivatives | D16: 0 | E16: 3 | F16: 0 | G16: 1
C17: Partial Derivatives | D17: 0 | E17: 4 | F17: 1 | G17: 1
C18: Indefinite Integrals | D18: 0 | E18: 3 | F18: 0 | G18: 0
C19: Partial Fractions | D19: 1 | E19: 2 | F19: 0 | G19: 0
C20: Trigonometric Functions | D20: 0 | E20: 2 | F20: 0 | G20: 1
C21: Definite Integrals | D21: 1 | E21: 5 | F21: 0 | G21: 1
B22: Numerical Methods | C22: Forward Rectangle Rule | D22: 0 | E22: 1 | F22: 0 | G22: 1
C23: Trapezoidal Rule | D23: 1 | E23: 5 | F23: 1 | G23: 1
C24: Simpson’s Rule | D24: 0 | E24: 2 | F24: 0 | G24: 0
C25: Taylor’s and McLaurin’s Series | D25: 0 | E25: 2 | F25: 0 | G25: 1
A26: Probability and Statistics | B26: Probability Distributions | C26: Probability- Basic Concepts | D26: 2 | E26: 8 | F26: 0 | G26: 1
C27: Binomial Distribution | D27: 1 | E27: 6 | F27: 1 | G27: 1
C28: Normal Distribution | D28: 0 | E28: 4 | F28: 0 | G28: 1
C29: Chi-squared distribution | D29: 2 | E29: 5 | F29: 0 | G29: 0
B30: Measures of Central Tendencies and Distribution | C30: Mean, Median Mode | D30: 0 | E30: 6 | F30: 0 | G30: 1
C31: Standard Deviation and Variance | D31: 0 | E31: 4 | F31: 0 | G31: 0
B32: Expected Value | C32: PDF and CDF | D32: 0 | E32: 1 | F32: 1 | G32: 0
C33: Expected Value of a Discrete Function | D33: 0 | E33: 4 | F33: 0 | G33: 0
B34: Regression, Curve Fitting, Goodness of Fit | C34: Regression and Curve Fitting | D34: 1 | E34: 8 | F34: 0 | G34: 0
B35: Hypothesis Testing | C35: t-distribution | D35: 0 | E35: 4 | F35: 0 | G35: 0
C36: ANOVA | D36: 0 | E36: 3 | F36: 0 | G36: 0
A37: Ethics and Professional Practice | B37: Codes of Ethics | C37: NCEES Model Law | D37: 0 | E37: 11 | F37: 0 | G37: 0
C38: Professional and Technical Societies | D38: 0 | E38: 1 | F38: 0 | G38: 0
C39: Ethical and Legal Considerations | D39: 0 | E39: 18 | F39: 0 | G39: 0
B40: Public Health, Safety and Welfare | C40: Public Health, Safety and Welfare in Engineering | D40: 0 | E40: 2 | F40: 0 | G40: 0
B41: Compliance with Codes, Standards and Regulations | C41: CWA
C42: CAA
C43: RCRA
C44: CERCLA
C45: CERCLA
C46: SDWA
C47: NEPA
C48: OSHA
B49: Societal Considerations | C49: Sustainability | D49: 0 | E49: 2 | F49: 0 | G49: 0
C50: Resiliency
C51: Long-Term Viability
A52: Engineering Economics | B52: Time Value of Money | C52: Discounted Cash Flow Factors | D52: 1 | E52: 5 | F52: 1 | G52: 1
C53: Net Present Value | D53: 0 | E53: 3 | F53: 0 | G53: 1
C54: Inflation | D54: 0 | E54: 3 | F54: 0 | G54: 0
B55: Cost Types and Breakdowns | C55: Cost Types | D55: 0 | E55: 3 | F55: 0 | G55: 0
B56: Economic Analyses | C56: Payback Period Analysis | D56: 0 | E56: 3 | F56: 0 | G56: 0
C57: Cost-Benefit Analysis | D57: 0 | E57: 2 | F57: 1 | G57: 0
C58: Break-Even Analysis | D58: 1 | E58: 14 | F58: 1 | G58: 1
C59: Overhead Analysis | D59: 0 | E59: 1 | F59: 0 | G59: 0
B60: Project Selection | C60: Comparison of Projects with Unequal Lives | D60: 0 | E60: 1 | F60: 0 | G60: 0
C61: Lease/Buy/Make | D61: 0 | E61: 2 | F61: 0 | G61: 0
C62: Depreciation | D62: 0 | E62: 4 | F62: 1 | G62: 0
A63: Fundamental Principles | B63: Population Projections and Demand Calculations | C63: Demand Calculations
B64: Reactors | C64: Batch | D64: 0 | E64: 2 | F64: 0 | G64: 0
C65: Semi-Batch | D65: 0 | E65: 1 | F65: 0 | G65: 0
C66: Continuous Stirred Tank | D66: 0 | E66: 1 | F66: 0 | G66: 0
C67: Plug Flow | D67: 0 | E67: 2 | F67: 0 | G67: 0
C68: Gas Phase | D68: 0 | E68: 0 | F68: 0 | G68: 0
C69: Liquid Phase | D69: 0 | E69: 0 | F69: 0 | G69: 0
B70: Material Science | C70: Mechanical Properties
C71: Electrical Properties
C72: Thermal Properties
C73: Chemical Properties
C74: Corrosion Terminology | D74: 0 | E74: 2 | F74: 0 | G74: 0
C75: Corrosion Mechanism | D75: 0 | E75: 3 | F75: 0 | G75: 0
C76: EMF Series | D76: 0 | E76: 3 | F76: 0 | G76: 0
C77: Galvanic Series | D77: 0 | E77: 1 | F77: 0 | G77: 0
C78: Corrosion Control | D78: 0 | E78: 4 | F78: 0 | G78: 0
C79: Stress
C80: Strain
A81: Environmental Chemistry | B81: Stoichiometry and Chemical Reactions | C81: Equilibrium
C82: Acid-Base | D82: 0 | E82: 5 | F82: 0 | G82: 0
C83: Oxidation-Reduction | D83: 0 | E83: 2 | F83: 0 | G83: 0
C84: Precipitation
C85: pH | D85: 0 | E85: 9 | F85: 0 | G85: 0
B86: Kinetics | C86: Chemical Conversion
C87: Growth and Decay
B88: Organic Chemistry | C88: Nomenclature | D88: 0 | E88: 5 | F88: 0 | G88: 0
C89: Reactions | D89: 0 | E89: 0 | F89: 0 | G89: 0
B90: Multimedia Equilibrium Partitioning | C90: Henry’s Law
C91: Octanol Partitioning Coefficient
A92: Health Hazards and Risk Assessment | B92: Dose-response Toxicity | C92: Carcinogens | D92: 0 | E92: 2 | F92: 0 | G92: 0
C93: Non-Carcinogens
B94: Exposure Routes and Pathways | C94: Exposure Routes and Pathways
B95: Occupational Health | C95: PPE | D95: 0 | E95: 1 | F95: 0 | G95: 0
C96: Noise Pollution
C97: Safety Screening
A98: Fluid Mechanics and Hydraulics | B98: Fluid Statics | C98: Pascal’s law | D98: 0 | E98: 9 | F98: 1 | G98: 0
C99: Pressure Measurement | D99: 1 | E99: 11 | F99: 0 | G99: 1
C100: Hydrostatic Forces on Submerged Surface | D100: 0 | E100: 16 | F100: 1 | G100: 0
C101: Archimedes Principle and Bouyancy | D101: 0 | E101: 15 | F101: 0 | G101: 0
...
